chrisdata/__init__.py
chrisdata/cli.py
chrisdata/dataset.py
chrisdata/learn.py
chrisdata/ner/__init__.py
chrisdata/ner/anatem.py
chrisdata/ner/gner.py
chrisdata/ner/gner_dataset.py
chrisdata/ner/hf_ner_dataset.py
chrisdata/net/__init__.py
chrisdata/net/check.py
chrisdata/wikidata/__init__.py
chrisdata/wikidata/convert_wikidata.py
chrisdata/wikidata/convert_wikidata1.py
chrisdata/wikidata/extract_wikidata.py
chrisdata/wikidata/filter_wikidata.py
chrisdata/wikidata/parse_wikidata.py
chrisdata/wikidata/restore_wikidata.py
chrisdata/wikidata/search_wikidata.py
chrisdata/wikipedia/__init__.py
chrisdata/wikipedia/convert_wikipedia.py
chrisdata/wikipedia/crawl_wikipedia.py
chrisdata/wikipedia/index_wikipedia.py
chrisdata/wikipedia/parse_wikipedia.py
chrisdata-0.5.2.dist-info/licenses/LICENSE
chrisdata-0.5.2.dist-info/METADATA
chrisdata-0.5.2.dist-info/WHEEL
chrisdata-0.5.2.dist-info/entry_points.txt
chrisdata-0.5.2.dist-info/top_level.txt
chrisdata-0.5.2.dist-info/zip-safe
chrisdata-0.5.2.dist-info/RECORD
