Metadata-Version: 2.4
Name: chrisdata
Version: 0.5.2
Summary: Data processing library
Home-page: https://github.com/chrisjihee/chrisdata
Author: Jihee Ryu
Author-email: chrisjihee@naver.com
Classifier: Development Status :: 3 - Alpha
Classifier: License :: OSI Approved :: MIT License
Classifier: Programming Language :: Python :: 3
Classifier: Programming Language :: Python :: 3.9
Classifier: Programming Language :: Python :: 3.10
Classifier: Programming Language :: Python :: 3.11
Classifier: Programming Language :: Python :: 3.12
License-File: LICENSE
Requires-Dist: chrisbase>=0.5.9
Requires-Dist: datasets
Requires-Dist: jsonlines
Requires-Dist: elasticsearch
Requires-Dist: beautifulsoup4
Requires-Dist: Wikipedia-API==0.6.0
Requires-Dist: qwikidata
Requires-Dist: Flask
Dynamic: license-file
